tweet_suite/__init__.py
tweet_suite/collect_tweets.py
tweet_suite/utils/__init__.py
tweet_suite/utils/database.py
tweet_suite/utils/geolocation.py
tweet_suite/utils/search.py
tweet_suite/utils/text_processing.py
tweet_suite/utils/datasets/la_keys.geojson
tweet_suite-1.1.4.data/scripts/collect_tweets
tweet_suite-1.1.4.dist-info/LICENSE
tweet_suite-1.1.4.dist-info/METADATA
tweet_suite-1.1.4.dist-info/WHEEL
tweet_suite-1.1.4.dist-info/top_level.txt
tweet_suite-1.1.4.dist-info/RECORD
