Metadata-Version: 2.1
Name: tweet-suite
Version: 1.1.4
Summary: Collect and save daily Twitter data from Wales using Twitter's Academic API.
Home-page: https://github.com/ninadicara/tweet-suite
Author: Nina Di Cara, Alastair Tanner, Valerio Maggio
Author-email: ninadicara@protonmail.com
License: UNKNOWN
Project-URL: Bug Tracker, https://github.com/ninadicara/tweet-suite/issues
Platform: UNKNOWN
Classifier: Programming Language :: Python :: 3
Classifier: License :: OSI Approved :: GNU General Public License v3 (GPLv3)
Classifier: Operating System :: OS Independent
Requires-Python: >=3.6,<3.10
License-File: LICENSE
Requires-Dist: retry
Requires-Dist: geopandas
Requires-Dist: vaderSentiment
Requires-Dist: schedule
Requires-Dist: pandas
Requires-Dist: shapley
Requires-Dist: requests
